aimcp/__init__.py
aimcp/__main__.py
aimcp/cache/__init__.py
aimcp/cache/factory.py
aimcp/cache/manager.py
aimcp/cache/models.py
aimcp/cache/protocol.py
aimcp/cache/storage.py
aimcp/config/__init__.py
aimcp/config/models.py
aimcp/gitlab/__init__.py
aimcp/gitlab/client.py
aimcp/gitlab/models.py
aimcp/server/__init__.py
aimcp/server/factory.py
aimcp/server/mcp_server.py
aimcp/tools/__init__.py
aimcp/tools/manager.py
aimcp/tools/models.py
aimcp/tools/resolver.py
aimcp/tools/resources.py
aimcp/utils/__init__.py
aimcp/utils/errors.py
aimcp/utils/health.py
aimcp/utils/logging.py
airulermcp-0.3.1.dist-info/METADATA
airulermcp-0.3.1.dist-info/WHEEL
airulermcp-0.3.1.dist-info/entry_points.txt
airulermcp-0.3.1.dist-info/licenses/LICENSE
airulermcp-0.3.1.dist-info/RECORD
