Metadata-Version: 2.4
Name: airulermcp
Version: 0.3.1
Summary: MCP server for distributing AI rules from GitLab repositories to IDEs
Project-URL: Homepage, https://github.com/junqed/aimcp
Project-URL: Documentation, https://github.com/junqed/aimcp#readme
Project-URL: Repository, https://github.com/junqed/aimcp
Project-URL: Issues, https://github.com/junqed/aimcp/issues
Author-email: Lenny <rusts-talus-9g@icloud.com>
Maintainer-email: Lenny <rusts-talus-9g@icloud.com>
License: MIT
License-File: LICENSE
Keywords: ai,gitlab,ide,mcp,model-context-protocol,tools
Classifier: Development Status :: 4 - Beta
Classifier: Intended Audience :: Developers
Classifier: License :: OSI Approved :: MIT License
Classifier: Operating System :: OS Independent
Classifier: Programming Language :: Python :: 3
Classifier: Programming Language :: Python :: 3.13
Classifier: Topic :: Software Development
Classifier: Topic :: Software Development :: Libraries :: Python Modules
Requires-Python: >=3.13
Requires-Dist: fastmcp>=2.0.0
Requires-Dist: httpx>=0.27.0
Requires-Dist: orjson>=3.11.3
Requires-Dist: pydantic-settings>=2.4.0
Requires-Dist: pydantic>=2.8.0
Requires-Dist: pyyaml>=6.0.0
Requires-Dist: structlog>=24.1.0
Requires-Dist: typer>=0.12.0
